navio2
