Metadata-Version: 1.0
Name: navio2
Version: 1.0.0
Summary: Navio 2 device drivers
Home-page: https://github.com/emlid/navio2
Author: Georgii Staroselskii
Author-email: georgii.staroselskii@emlid.com
License: BSD
Platform: UNKNOWN
